TextUtilities/__init__.py
TextUtilities/color/__init__.py
text_utilities-0.0.0.0.2.dist-info/LICENSE
text_utilities-0.0.0.0.2.dist-info/METADATA
text_utilities-0.0.0.0.2.dist-info/WHEEL
text_utilities-0.0.0.0.2.dist-info/top_level.txt
text_utilities-0.0.0.0.2.dist-info/RECORD
