Metadata-Version: 2.1
Name: text-utilities
Version: 0.0.0.0.2
Summary: A package that provides utilities for text
Author-email: Joseph Knutson <jmknutson2012@gmail.com>
License: MIT License
Project-URL: Homepage, https://github.com/Joey1222/TextUtilities
Project-URL: Issues, https://github.com/Joey1222/TextUtilities/issues
Keywords: text,setuptools,development
Classifier: Programming Language :: Python :: 3
Classifier: License :: OSI Approved :: MIT License
Classifier: Operating System :: OS Independent
Requires-Python: >=3.8
License-File: LICENSE
